thermotecaeroflowflexismart/__init__.py
thermotecaeroflowflexismart/client.py
thermotecaeroflowflexismart/communication.py
thermotecaeroflowflexismart/const.py
thermotecaeroflowflexismart/data_object.py
thermotecaeroflowflexismart/exception.py
thermotecaeroflowflexismart/utils.py
thermotecaeroflowflexismart-0.1.0.dist-info/licenses/LICENSE
thermotecaeroflowflexismart-0.1.0.dist-info/METADATA
thermotecaeroflowflexismart-0.1.0.dist-info/WHEEL
thermotecaeroflowflexismart-0.1.0.dist-info/top_level.txt
thermotecaeroflowflexismart-0.1.0.dist-info/RECORD
