Metadata-Version: 2.4
Name: thermotecaeroflowflexismart
Version: 0.1.0
Summary: Python Thermotec AeroFlow® Library
Home-page: https://github.com/KaiGrassnick/py-thermotec-aeroflow-flexismart
Author: Kai Grassnick
Author-email: py-thermotec-aeroflow-flexismart@kai-grassnick.de
License: GNU GPLv3
Requires-Python: >=3.11
License-File: LICENSE
Requires-Dist: asyncio_dgram
Dynamic: author
Dynamic: author-email
Dynamic: description
Dynamic: description-content-type
Dynamic: home-page
Dynamic: license
Dynamic: license-file
Dynamic: requires-dist
Dynamic: requires-python
Dynamic: summary
